{
    "type": "array",
    "items": {
        "type": "object",
        "properties": {
            "lat": {
                "type": "string",
                "examples": [
                    "39.7456"
                ]
            },
            "lon": {
                "type": "string",
                "examples": [
                    "-97.0892"
                ]
            },
            "date": {
                "type": "string",
                "examples": [
                    "2024-09-10"
                ],
                "pattern": "\\d\\d\\d\\d-\\d\\d-\\d\\d"
            },
            "hour": {
                "type": "number",
                "examples": [
                    12,
                    20
                ],
                "minimum": 0,
                "maximum": 23
            }
        }
    },
    "minItems":1
}